cuteagent/__init__.py
cuteagent/common.py
cuteagent/cuteagent copy.py
cuteagent/cuteagent.py
cuteagent-0.2.26.dist-info/licenses/LICENSE
cuteagent-0.2.26.dist-info/METADATA
cuteagent-0.2.26.dist-info/WHEEL
cuteagent-0.2.26.dist-info/entry_points.txt
cuteagent-0.2.26.dist-info/top_level.txt
cuteagent-0.2.26.dist-info/RECORD
