Metadata-Version: 2.4
Name: cuteagent
Version: 0.2.26
Summary: Computer Use Task Execution Agent
Author-email: Masoud Jb <eng@fintor.com>
License: MIT License
Project-URL: Homepage, https://github.com/MasoudJB/cuteagent
Keywords: cuteagent,openai
Classifier: Intended Audience :: Developers
Classifier: License :: OSI Approved :: MIT License
Classifier: Natural Language :: English
Classifier: Programming Language :: Python :: 3.8
Classifier: Programming Language :: Python :: 3.9
Classifier: Programming Language :: Python :: 3.10
Classifier: Programming Language :: Python :: 3.11
Classifier: Programming Language :: Python :: 3.12
Requires-Python: >=3.8
License-File: LICENSE
Requires-Dist: numpy
Requires-Dist: gradio_client
Requires-Dist: openai
Requires-Dist: python-dotenv
Requires-Dist: langgraph-sdk
Requires-Dist: anthropic
Provides-Extra: all
Requires-Dist: cuteagent[extra]; extra == "all"
Provides-Extra: extra
Requires-Dist: pandas; extra == "extra"
Dynamic: license-file
